a_pandas_ex_automate_win32/LICENSE
a_pandas_ex_automate_win32/README.MD
a_pandas_ex_automate_win32/__init__.py
a_pandas_ex_automate_win32/requirements.txt
a_pandas_ex_automate_win32/thirdparty.json
a_pandas_ex_automate_win32-0.12.dist-info/LICENSE.rst
a_pandas_ex_automate_win32-0.12.dist-info/METADATA
a_pandas_ex_automate_win32-0.12.dist-info/WHEEL
a_pandas_ex_automate_win32-0.12.dist-info/top_level.txt
a_pandas_ex_automate_win32-0.12.dist-info/RECORD
