Metadata-Version: 2.1
Name: a-pandas-ex-automate-win32
Version: 0.12
Summary: Automate the Microsoft Windows GUI with Pandas! Without pywin32, only ctypes!
Home-page: https://github.com/hansalemaos/a_pandas_ex_automate_win32
Author: Johannes Fischer
Author-email: <aulasparticularesdealemaosp@gmail.com>
License: MIT
Keywords: ctypes,windows,Pandas,DataFrame,pyautogui,pywinauto
Classifier: Development Status :: 4 - Beta
Classifier: Programming Language :: Python :: 3 :: Only
Classifier: Programming Language :: Python :: 3.9
Classifier: Topic :: Scientific/Engineering :: Visualization
Classifier: Topic :: Software Development :: Libraries :: Python Modules
Classifier: Topic :: Text Editors :: Text Processing
Classifier: Topic :: Text Processing :: General
Classifier: Topic :: Text Processing :: Indexing
Classifier: Topic :: Text Processing :: Filters
Classifier: Topic :: Utilities
License-File: LICENSE.rst
Requires-Dist: a-pandas-ex-apply-ignore-exceptions
Requires-Dist: flatten-everything
Requires-Dist: pandas
